zgli/__init__.py
zgli/encoder.py
zgli/folder.py
zgli/tree.py
zgli-0.2.0.dist-info/LICENSE
zgli-0.2.0.dist-info/METADATA
zgli-0.2.0.dist-info/WHEEL
zgli-0.2.0.dist-info/top_level.txt
zgli-0.2.0.dist-info/RECORD
