Metadata-Version: 2.1
Name: zgli
Version: 0.2.0
Summary: Perfrom clustering by compression using python.
Home-page: https://zgly-92273.web.app/index.html
Author: Diogo Azevedo
Author-email: diogoazevedo15@gmail.com
Classifier: Programming Language :: Python :: 3
Classifier: License :: OSI Approved :: MIT License
Classifier: Operating System :: OS Independent
Requires-Python: >=3.7
License-File: LICENSE
Requires-Dist: numpy
Requires-Dist: pandas
Requires-Dist: multiprocess
Requires-Dist: tqdm
Requires-Dist: IPython
Requires-Dist: graphviz
